openedx_caliper_tracking/__init__.py
openedx_caliper_tracking/apps.py
openedx_caliper_tracking/base_transformer.py
openedx_caliper_tracking/caliper_config.py
openedx_caliper_tracking/exceptions.py
openedx_caliper_tracking/kafka_utils.py
openedx_caliper_tracking/loggers.py
openedx_caliper_tracking/pavement.py
openedx_caliper_tracking/processor.py
openedx_caliper_tracking/run_certification_process.py
openedx_caliper_tracking/settings.py
openedx_caliper_tracking/tasks.py
openedx_caliper_tracking/utils.py
openedx_caliper_tracking/tests/__init__.py
openedx_caliper_tracking/tests/factories.py
openedx_caliper_tracking/tests/test_caliper_delivery.py
openedx_caliper_tracking/tests/test_caliper_kafka.py
openedx_caliper_tracking/tests/test_caliper_transformers.py
openedx_caliper_tracking/tests/test_requirements.txt
openedx_caliper_tracking/tests/test_utils.py
openedx_caliper_tracking/tests/testing_backend.py
openedx_caliper_tracking/tests/current/book.json
openedx_caliper_tracking/tests/current/edx.bi.course.upgrade.sidebarupsell.displayed.json
openedx_caliper_tracking/tests/current/edx.bi.email.sent.json
openedx_caliper_tracking/tests/current/edx.bi.schedule.suppressed.json
openedx_caliper_tracking/tests/current/edx.bi.user.account.authenticated(third_party_oauth).json
openedx_caliper_tracking/tests/current/edx.bi.user.account.authenticated.json
openedx_caliper_tracking/tests/current/edx.bi.user.account.linked.json
openedx_caliper_tracking/tests/current/edx.bi.user.account.registered.json
openedx_caliper_tracking/tests/current/edx.bi.user.certificate.generate.json
openedx_caliper_tracking/tests/current/edx.bi.user.org_email.opted_in.json
openedx_caliper_tracking/tests/current/edx.bi.user.org_email.opted_out.json
openedx_caliper_tracking/tests/current/edx.bi.verify.submitted.json
openedx_caliper_tracking/tests/current/edx.bookmark.accessed.json
openedx_caliper_tracking/tests/current/edx.bookmark.added.json
openedx_caliper_tracking/tests/current/edx.bookmark.listed.json
openedx_caliper_tracking-0.14.3.dist-info/LICENSE
openedx_caliper_tracking-0.14.3.dist-info/METADATA
openedx_caliper_tracking-0.14.3.dist-info/WHEEL
openedx_caliper_tracking-0.14.3.dist-info/top_level.txt
openedx_caliper_tracking-0.14.3.dist-info/RECORD
