Metadata-Version: 2.1
Name: openedx-caliper-tracking
Version: 0.14.3
Summary: Open edX Caliper Tracking app can be used to transform Open edX tracking events into Caliper standard compliant events.
Home-page: https://github.com/ucsd-ets/caliper-tracking
Author: UC San Diego
Author-email: UNKNOWN
License: GPL 3.0
Platform: UNKNOWN
Classifier: Environment :: Web Environment
Classifier: Framework :: Django
Classifier: Framework :: Django :: 1.11
Classifier: Intended Audience :: Developers
Classifier: License :: OSI Approved :: GNU Affero General Public License v3 or later (AGPLv3+)
Classifier: Operating System :: OS Independent
Classifier: Programming Language :: Python
Classifier: Programming Language :: Python :: 2
Classifier: Programming Language :: Python :: 2.7
Classifier: Topic :: Internet :: WWW/HTTP
Requires-Dist: kafka-python (==2.0.1)
